ingrab/__init__.py
ingrab/downloader.py
ingrab/tempCodeRunnerFile.py
ingrab-1.3.3.dist-info/LICENSE
ingrab-1.3.3.dist-info/METADATA
ingrab-1.3.3.dist-info/WHEEL
ingrab-1.3.3.dist-info/entry_points.txt
ingrab-1.3.3.dist-info/top_level.txt
ingrab-1.3.3.dist-info/RECORD
