Metadata-Version: 2.1
Name: ingrab
Version: 1.3.3
Summary: A user-friendly application for downloading posts and reels from Instagram profiles.
Home-page: https://github.com/ishubtripathi/Ingrab.git
Author: Shubh Tripathi
Author-email: bugingrab@gmail.com
Keywords: ingrab,InGrabe,instagram,insta,post,reel,downloader,cli
Classifier: Programming Language :: Python :: 3
Classifier: License :: OSI Approved :: MIT License
Classifier: Operating System :: Unix
Classifier: Operating System :: MacOS :: MacOS X
Classifier: Operating System :: Microsoft :: Windows
Requires-Python: >=3
License-File: LICENSE
Requires-Dist: instaloader
